django_emulate_aws_env-0.2.0.dist-info/DESCRIPTION.rst
django_emulate_aws_env-0.2.0.dist-info/METADATA
django_emulate_aws_env-0.2.0.dist-info/RECORD
django_emulate_aws_env-0.2.0.dist-info/WHEEL
django_emulate_aws_env-0.2.0.dist-info/metadata.json
django_emulate_aws_env-0.2.0.dist-info/top_level.txt
emulate_aws_env/__init__.py
emulate_aws_env/middleware.py
