Metadata-Version: 2.0
Name: django-emulate-aws-env
Version: 0.2.0
Summary: Emulates the conditions of an AWS "Serverless" environment (API Gateway + Lambda) in your test and development environments.
Home-page: https://github.com/danielholmes/django-emulate-aws-env
Author: Daniel Holmes
Author-email: daniel@danielholmes.org
License: MIT
Keywords: django-emulate-aws-env
Platform: UNKNOWN
Classifier: Development Status :: 3 - Alpha
Classifier: Framework :: Django
Classifier: Framework :: Django :: 1.8
Classifier: Framework :: Django :: 1.9
Classifier: Framework :: Django :: 1.10
Classifier: Intended Audience :: Developers
Classifier: License :: OSI Approved :: BSD License
Classifier: Natural Language :: English
Classifier: Programming Language :: Python :: 2
Classifier: Programming Language :: Python :: 2.7
Classifier: Programming Language :: Python :: 3
Classifier: Programming Language :: Python :: 3.6
